{
  "checked_at": "2026-05-18 15:16:37 (Hora Colombia)",
  "confirmed": 1,
  "signals": [
    {
      "ticker": "LRCX",
      "composite": 80,
      "prob": 95,
      "zones": {
        "entry": 280.45,
        "tp1": 293.26,
        "tp2": 301.8,
        "sl": 279.03
      },
      "periods": [
        "1 Mes",
        "3 Meses",
        "6 Meses",
        "1 A\u00f1o"
      ]
    }
  ],
  "watchlist": [
    {
      "ticker": "CF",
      "failed": [
        "Radar"
      ]
    },
    {
      "ticker": "APA",
      "failed": [
        "Radar"
      ]
    },
    {
      "ticker": "EOG",
      "failed": [
        "Radar"
      ]
    },
    {
      "ticker": "MU",
      "failed": [
        "Radar"
      ]
    },
    {
      "ticker": "AMAT",
      "failed": [
        "Radar"
      ]
    },
    {
      "ticker": "NXPI",
      "failed": [
        "Radar"
      ]
    },
    {
      "ticker": "NXPI",
      "failed": [
        "Radar"
      ]
    },
    {
      "ticker": "TRGP",
      "failed": [
        "Analysis"
      ]
    },
    {
      "ticker": "STLD",
      "failed": [
        "Radar"
      ]
    },
    {
      "ticker": "NVDA",
      "failed": [
        "Radar"
      ]
    },
    {
      "ticker": "MPWR",
      "failed": [
        "Radar"
      ]
    },
    {
      "ticker": "MPWR",
      "failed": [
        "Radar"
      ]
    },
    {
      "ticker": "KO",
      "failed": [
        "Analysis"
      ]
    },
    {
      "ticker": "HAL",
      "failed": [
        "Radar"
      ]
    },
    {
      "ticker": "WCC",
      "failed": [
        "Radar"
      ]
    }
  ]
}